{"15": {"win_rate": "100.00", "top_four_rate": "100.00", "pick_rate": "6.42"}, "36": {"win_rate": "100.00", "top_four_rate": "100.00", "pick_rate": "5.19"}, "44": {"win_rate": "100.00", "top_four_rate": "100.00", "pick_rate": "4.35"}, "77": {"win_rate": "100.00", "top_four_rate": "100.00", "pick_rate": "4.13"}, "37": {"win_rate": "100.00", "top_four_rate": "100.00", "pick_rate": "4.11"}, "29": {"win_rate": "100.00", "top_four_rate": "100.00", "pick_rate": "4.00"}, "19": {"win_rate": "100.00", "top_four_rate": "100.00", "pick_rate": "3.95"}, "14": {"win_rate": "100.00", "top_four_rate": "100.00", "pick_rate": "3.32"}, "59": {"win_rate": "100.00", "top_four_rate": "100.00", "pick_rate": "3.18"}, "69": {"win_rate": "100.00", "top_four_rate": "100.00", "pick_rate": "2.93"}, "67": {"win_rate": "100.00", "top_four_rate": "100.00", "pick_rate": "2.83"}, "12": {"win_rate": "100.00", "top_four_rate": "100.00", "pick_rate": "2.73"}, "23": {"win_rate": "100.00", "top_four_rate": "100.00", "pick_rate": "2.68"}, "33": {"win_rate": "100.00", "top_four_rate": "100.00", "pick_rate": "2.51"}, "45": {"win_rate": "100.00", "top_four_rate": "100.00", "pick_rate": "2.50"}, "26": {"win_rate": "100.00", "top_four_rate": "100.00", "pick_rate": "2.44"}, "99": {"win_rate": "100.00", "top_four_rate": "100.00", "pick_rate": "2.41"}, "55": {"win_rate": "100.00", "top_four_rate": "100.00", "pick_rate": "2.39"}, "22": {"win_rate": "100.00", "top_four_rate": "100.00", "pick_rate": "2.31"}, "47": {"win_rate": "100.00", "top_four_rate": "100.00", "pick_rate": "2.24"}, "79": {"win_rate": "100.00", "top_four_rate": "100.00", "pick_rate": "2.13"}, "27": {"win_rate": "100.00", "top_four_rate": "100.00", "pick_rate": "2.09"}, "34": {"win_rate": "100.00", "top_four_rate": "100.00", "pick_rate": "1.92"}, "16": {"win_rate": "100.00", "top_four_rate": "100.00", "pick_rate": "1.90"}, "39": {"win_rate": "100.00", "top_four_rate": "100.00", "pick_rate": "1.89"}, "35": {"win_rate": "100.00", "top_four_rate": "100.00", "pick_rate": "1.64"}, "46": {"win_rate": "100.00", "top_four_rate": "100.00", "pick_rate": "1.63"}, "66": {"win_rate": "100.00", "top_four_rate": "100.00", "pick_rate": "1.59"}, "17": {"win_rate": "100.00", "top_four_rate": "100.00", "pick_rate": "1.36"}, "11": {"win_rate": "100.00", "top_four_rate": "100.00", "pick_rate": "1.32"}, "57": {"win_rate": "100.00", "top_four_rate": "100.00", "pick_rate": "1.29"}, "25": {"win_rate": "100.00", "top_four_rate": "100.00", "pick_rate": "1.22"}, "24": {"win_rate": "100.00", "top_four_rate": "100.00", "pick_rate": "1.18"}, "49": {"win_rate": "100.00", "top_four_rate": "100.00", "pick_rate": "1.17"}, "13": {"win_rate": "100.00", "top_four_rate": "100.00", "pick_rate": "1.07"}, "78": {"win_rate": "100.00", "top_four_rate": "100.00", "pick_rate": "1.04"}, "89": {"win_rate": "100.00", "top_four_rate": "100.00", "pick_rate": "0.88"}, "56": {"win_rate": "100.00", "top_four_rate": "100.00", "pick_rate": "0.88"}, "4": {"win_rate": "100.00", "top_four_rate": "100.00", "pick_rate": "0.74"}, "2": {"win_rate": "100.00", "top_four_rate": "100.00", "pick_rate": "0.73"}, "68": {"win_rate": "100.00", "top_four_rate": "100.00", "pick_rate": "0.72"}, "3": {"win_rate": "100.00", "top_four_rate": "100.00", "pick_rate": "0.68"}, "48": {"win_rate": "100.00", "top_four_rate": "100.00", "pick_rate": "0.54"}, "88": {"win_rate": "100.00", "top_four_rate": "100.00", "pick_rate": "0.53"}, "28": {"win_rate": "100.00", "top_four_rate": "100.00", "pick_rate": "0.52"}, "6": {"win_rate": "100.00", "top_four_rate": "100.00", "pick_rate": "0.51"}, "7": {"win_rate": "100.00", "top_four_rate": "100.00", "pick_rate": "0.46"}, "5": {"win_rate": "100.00", "top_four_rate": "100.00", "pick_rate": "0.40"}, "1": {"win_rate": "100.00", "top_four_rate": "100.00", "pick_rate": "0.38"}, "9": {"win_rate": "100.00", "top_four_rate": "100.00", "pick_rate": "0.30"}, "18": {"win_rate": "100.00", "top_four_rate": "100.00", "pick_rate": "0.30"}, "38": {"win_rate": "100.00", "top_four_rate": "100.00", "pick_rate": "0.20"}, "58": {"win_rate": "100.00", "top_four_rate": "100.00", "pick_rate": "0.17"}, "8": {"win_rate": "100.00", "top_four_rate": "100.00", "pick_rate": "0.07"}}