{"Astro": {"win_rate": "10.98", "top_four_rate": "47.83", "pick_rate": "4.54", "average_units": "1.38", "average_tier": "0.15", "average_placement": 4.6}, "Battlecast": {"win_rate": "15.09", "top_four_rate": "52.54", "pick_rate": "5.49", "average_units": "1.74", "average_tier": "0.53", "average_placement": 4.4}, "Blademaster": {"win_rate": "13.89", "top_four_rate": "52.19", "pick_rate": "5.41", "average_units": "2.17", "average_tier": "0.39", "average_placement": 4.4}, "Blaster": {"win_rate": "10.37", "top_four_rate": "46.65", "pick_rate": "4.64", "average_units": "1.84", "average_tier": "0.81", "average_placement": 4.7}, "Brawler": {"win_rate": "10.94", "top_four_rate": "48.60", "pick_rate": "6.26", "average_units": "2.25", "average_tier": "0.88", "average_placement": 4.6}, "Celestial": {"win_rate": "16.87", "top_four_rate": "55.06", "pick_rate": "2.89", "average_units": "1.44", "average_tier": "0.38", "average_placement": 4.2}, "Chrono": {"win_rate": "13.00", "top_four_rate": "51.42", "pick_rate": "9.83", "average_units": "1.93", "average_tier": "0.81", "average_placement": 4.4}, "Cybernetic": {"win_rate": "12.46", "top_four_rate": "50.58", "pick_rate": "5.89", "average_units": "2.84", "average_tier": "0.71", "average_placement": 4.5}, "DarkStar": {"win_rate": "14.53", "top_four_rate": "52.49", "pick_rate": "4.13", "average_units": "1.53", "average_tier": "0.47", "average_placement": 4.4}, "Demolitionist": {"win_rate": "11.43", "top_four_rate": "50.20", "pick_rate": "2.23", "average_units": "1.54", "average_tier": "0.54", "average_placement": 4.5}, "Infiltrator": {"win_rate": "13.22", "top_four_rate": "53.84", "pick_rate": "6.03", "average_units": "1.46", "average_tier": "0.42", "average_placement": 4.3}, "ManaReaver": {"win_rate": "15.79", "top_four_rate": "56.65", "pick_rate": "4.08", "average_units": "1.32", "average_tier": "0.32", "average_placement": 4.2}, "MechPilot": {"win_rate": "14.35", "top_four_rate": "55.94", "pick_rate": "3.75", "average_units": "1.80", "average_tier": "0.32", "average_placement": 4.2}, "Mercenary": {"win_rate": "15.53", "top_four_rate": "58.25", "pick_rate": "1.14", "average_units": "1.00", "average_tier": "1.00", "average_placement": 4.1}, "Mystic": {"win_rate": "15.09", "top_four_rate": "51.71", "pick_rate": "4.02", "average_units": "2.20", "average_tier": "0.96", "average_placement": 4.4}, "Protector": {"win_rate": "22.26", "top_four_rate": "56.91", "pick_rate": "2.18", "average_units": "1.57", "average_tier": "0.47", "average_placement": 4.1}, "Rebel": {"win_rate": "15.19", "top_four_rate": "53.15", "pick_rate": "4.89", "average_units": "2.89", "average_tier": "0.81", "average_placement": 4.3}, "Sniper": {"win_rate": "10.46", "top_four_rate": "45.52", "pick_rate": "3.12", "average_units": "1.89", "average_tier": "0.79", "average_placement": 4.7}, "Sorcerer": {"win_rate": "12.99", "top_four_rate": "53.51", "pick_rate": "3.53", "average_units": "3.82", "average_tier": "1.77", "average_placement": 4.3}, "SpacePirate": {"win_rate": "12.99", "top_four_rate": "50.21", "pick_rate": "2.64", "average_units": "1.14", "average_tier": "0.10", "average_placement": 4.5}, "StarGuardian": {"win_rate": "15.62", "top_four_rate": "55.50", "pick_rate": "4.75", "average_units": "2.15", "average_tier": "0.43", "average_placement": 4.2}, "Starship": {"win_rate": "21.12", "top_four_rate": "66.35", "pick_rate": "2.81", "average_units": "0.99", "average_tier": "0.99", "average_placement": 3.6}, "Vanguard": {"win_rate": "11.09", "top_four_rate": "46.10", "pick_rate": "4.46", "average_units": "2.26", "average_tier": "0.99", "average_placement": 4.7}, "Paragon": {"win_rate": "19.55", "top_four_rate": "67.24", "pick_rate": "1.29", "average_units": "0.99", "average_tier": "0.99", "average_placement": 3.6}}