{"Blademaster": {"win_rate": "12.62", "top_four_rate": "50.44", "pick_rate": "5.45", "average_units": "2.50", "average_tier": "0.65", "average_placement": 4.5}, "Blaster": {"win_rate": "13.20", "top_four_rate": "51.49", "pick_rate": "4.86", "average_units": "2.18", "average_tier": "0.89", "average_placement": 4.4}, "Brawler": {"win_rate": "13.49", "top_four_rate": "51.43", "pick_rate": "4.97", "average_units": "2.72", "average_tier": "1.17", "average_placement": 4.4}, "Celestial": {"win_rate": "13.66", "top_four_rate": "52.15", "pick_rate": "5.18", "average_units": "2.34", "average_tier": "1.03", "average_placement": 4.4}, "Chrono": {"win_rate": "12.72", "top_four_rate": "51.11", "pick_rate": "8.34", "average_units": "2.04", "average_tier": "0.90", "average_placement": 4.4}, "Cybernetic": {"win_rate": "12.19", "top_four_rate": "51.87", "pick_rate": "6.30", "average_units": "1.67", "average_tier": "0.23", "average_placement": 4.4}, "DarkStar": {"win_rate": "12.59", "top_four_rate": "50.27", "pick_rate": "5.01", "average_units": "1.88", "average_tier": "0.25", "average_placement": 4.5}, "Demolitionist": {"win_rate": "14.76", "top_four_rate": "50.83", "pick_rate": "3.29", "average_units": "1.75", "average_tier": "0.70", "average_placement": 4.4}, "Infiltrator": {"win_rate": "13.94", "top_four_rate": "51.27", "pick_rate": "3.54", "average_units": "2.29", "average_tier": "0.97", "average_placement": 4.4}, "ManaReaver": {"win_rate": "13.18", "top_four_rate": "50.55", "pick_rate": "4.55", "average_units": "1.85", "average_tier": "0.73", "average_placement": 4.5}, "MechPilot": {"win_rate": "13.94", "top_four_rate": "51.15", "pick_rate": "2.73", "average_units": "1.74", "average_tier": "0.36", "average_placement": 4.4}, "Mercenary": {"win_rate": "16.41", "top_four_rate": "58.19", "pick_rate": "4.30", "average_units": "1.15", "average_tier": "1.00", "average_placement": 4.0}, "Mystic": {"win_rate": "16.28", "top_four_rate": "56.97", "pick_rate": "4.06", "average_units": "1.66", "average_tier": "0.63", "average_placement": 4.1}, "Protector": {"win_rate": "12.48", "top_four_rate": "52.18", "pick_rate": "1.88", "average_units": "1.86", "average_tier": "0.72", "average_placement": 4.4}, "Rebel": {"win_rate": "13.32", "top_four_rate": "51.28", "pick_rate": "4.53", "average_units": "2.62", "average_tier": "0.64", "average_placement": 4.4}, "Sniper": {"win_rate": "11.21", "top_four_rate": "48.36", "pick_rate": "2.95", "average_units": "1.80", "average_tier": "0.79", "average_placement": 4.6}, "Sorcerer": {"win_rate": "13.63", "top_four_rate": "50.97", "pick_rate": "3.78", "average_units": "2.68", "average_tier": "1.26", "average_placement": 4.5}, "SpacePirate": {"win_rate": "13.15", "top_four_rate": "50.15", "pick_rate": "4.66", "average_units": "1.38", "average_tier": "0.30", "average_placement": 4.5}, "StarGuardian": {"win_rate": "15.18", "top_four_rate": "55.68", "pick_rate": "2.57", "average_units": "1.92", "average_tier": "0.34", "average_placement": 4.2}, "Starship": {"win_rate": "17.82", "top_four_rate": "63.04", "pick_rate": "1.04", "average_units": "1.00", "average_tier": "1.00", "average_placement": 3.8}, "Valkyrie": {"win_rate": "13.07", "top_four_rate": "51.26", "pick_rate": "5.25", "average_units": "1.48", "average_tier": "0.48", "average_placement": 4.4}, "Vanguard": {"win_rate": "11.47", "top_four_rate": "46.83", "pick_rate": "4.65", "average_units": "1.82", "average_tier": "0.76", "average_placement": 4.7}, "Void": {"win_rate": "13.14", "top_four_rate": "52.37", "pick_rate": "4.56", "average_units": "1.55", "average_tier": "0.26", "average_placement": 4.4}}