{"team_comp_2": {"comp_name": "Cybernetic & Blademaster", "Thumbnail_picture": "Irelia", "Count": 3481.0, "Placement": 4.68, "Trait_tiers": {"blademaster": 1, "chrono": 1, "cybernetic": 2, "manareaver": 1, "vanguard": 1}, "Champions": {"Irelia": {"Count": 98, "Items": ["19", "29", "15"], "isCarry": true}, "Vi": {"Count": 97, "Items": ["36", "45"]}, "Vayne": {"Count": 96, "Items": ["29", "19", "12"], "isCarry": true}, "Leona": {"Count": 91, "Items": ["36", "67", "47"], "isCarry": true}, "Fiora": {"Count": 87, "Items": ["47", "4", "67"]}, "Ekko": {"Count": 74, "Items": ["57", "37", "36"]}, "Thresh": {"Count": 55, "Items": []}, "WuKong": {"Count": 44, "Items": []}, "Lucian": {"Count": 42, "Items": ["57"]}, "Riven": {"Count": 41, "Items": []}}}, "team_comp_4": {"comp_name": "Brawler & Rebel", "Thumbnail_picture": "Jinx", "Count": 2883.0, "Placement": 4.46, "Trait_tiers": {"brawler": 2, "blaster": 1, "chrono": 1, "rebel": 1, "starship": 1}, "Champions": {"Jinx": {"Count": 92, "Items": ["12", "57", "29"], "isCarry": true}, "Ezreal": {"Count": 87, "Items": ["57"]}, "Malphite": {"Count": 81, "Items": []}, "Blitzcrank": {"Count": 80, "Items": ["67"]}, "Gnar": {"Count": 79, "Items": ["36", "45", "66"], "isCarry": true}, "Vi": {"Count": 67, "Items": ["36", "45"]}, "AurelionSol": {"Count": 54, "Items": ["37", "33"]}}}, "team_comp_1": {"comp_name": "Sorcerer & Starguardian", "Thumbnail_picture": "Syndra", "Count": 2764.0, "Placement": 4.59, "Trait_tiers": {"chrono": 1, "sorcerer": 3, "starguardian": 1, "paragon": 1}, "Champions": {"Syndra": {"Count": 86, "Items": ["46"]}, "Viktor": {"Count": 84, "Items": ["37", "48", "12"], "isCarry": true}, "Zoe": {"Count": 82, "Items": []}, "Ahri": {"Count": 81, "Items": ["46"]}, "TwistedFate": {"Count": 66, "Items": []}, "Xerath": {"Count": 52, "Items": ["23", "69"]}, "Annie": {"Count": 50, "Items": ["27"]}, "Janna": {"Count": 42, "Items": ["46"]}, "Riven": {"Count": 41, "Items": ["33", "69", "15"], "isCarry": true}}}, "team_comp_6": {"comp_name": "Sniper & Astro", "Thumbnail_picture": "Nautilus", "Count": 2194.0, "Placement": 4.38, "Trait_tiers": {"celestial": 1, "chrono": 1, "mystic": 1, "sniper": 2, "vanguard": 1, "astro": 1}, "Champions": {"Nautilus": {"Count": 100, "Items": []}, "Teemo": {"Count": 99, "Items": ["37", "33", "34"], "isCarry": true}, "Jhin": {"Count": 98, "Items": ["19", "29", "15"], "isCarry": true}, "Gnar": {"Count": 96, "Items": ["36", "55", "45"], "isCarry": true}, "WuKong": {"Count": 92, "Items": ["36", "45", "55"]}, "Ashe": {"Count": 75, "Items": []}, "Caitlyn": {"Count": 59, "Items": []}, "Lulu": {"Count": 51, "Items": []}, "Karma": {"Count": 51, "Items": []}}}, "team_comp_7": {"comp_name": "Mystic & Vanguard", "Thumbnail_picture": "Cassiopeia", "Count": 2190.0, "Placement": 3.69, "Trait_tiers": {"chrono": 1, "mystic": 2, "vanguard": 1}, "Champions": {"Cassiopeia": {"Count": 99, "Items": ["37", "22", "34"], "isCarry": true}, "Jayce": {"Count": 98, "Items": ["15", "36", "66"], "isCarry": true}, "Karma": {"Count": 97, "Items": []}, "Nautilus": {"Count": 97, "Items": []}, "WuKong": {"Count": 97, "Items": ["99", "36", "15"], "isCarry": true}, "Soraka": {"Count": 94, "Items": []}, "Mordekaiser": {"Count": 93, "Items": []}, "Lulu": {"Count": 77, "Items": ["14"]}, "Thresh": {"Count": 41, "Items": []}}}, "team_comp_3": {"comp_name": "Protector & Mystic", "Thumbnail_picture": "Rakan", "Count": 1832.0, "Placement": 4.73, "Trait_tiers": {"celestial": 1, "mystic": 2, "protector": 2, "battlecast": 1}, "Champions": {"Rakan": {"Count": 78, "Items": ["14", "37", "36"]}, "XinZhao": {"Count": 74, "Items": ["55", "66", "25"], "isCarry": true}, "Cassiopeia": {"Count": 67, "Items": ["37", "78", "33"], "isCarry": true}, "Neeko": {"Count": 64, "Items": ["15"]}, "Karma": {"Count": 64, "Items": []}, "JarvanIV": {"Count": 62, "Items": []}, "Soraka": {"Count": 59, "Items": []}, "Urgot": {"Count": 50, "Items": ["14", "15", "22"], "isCarry": true}, "Lulu": {"Count": 46, "Items": []}}}, "team_comp_5": {"comp_name": "Blademaster & Rebel", "Thumbnail_picture": "MasterYi", "Count": 1038.0, "Placement": 4.68, "Trait_tiers": {"blademaster": 1, "chrono": 1, "rebel": 1}, "Champions": {"MasterYi": {"Count": 93, "Items": ["69", "23", "22"], "isCarry": true}, "Yasuo": {"Count": 93, "Items": ["17", "14", "15"], "isCarry": true}, "Shen": {"Count": 91, "Items": ["47", "45"]}, "Riven": {"Count": 87, "Items": ["37", "33"]}, "Zed": {"Count": 77, "Items": ["18", "19", "22"], "isCarry": true}, "Irelia": {"Count": 73, "Items": ["19"]}}}}