{"champions": {"Ahri": "53.34", "Annie": "58.04", "Ashe": "50.95", "AurelionSol": "84.05", "Bard": "33.80", "Blitzcrank": "51.70", "Caitlyn": "47.77", "Cassiopeia": "86.24", "Ezreal": "71.56", "Ekko": "85.75", "Darius": "43.55", "Fiora": "62.23", "Fizz": "61.50", "Gangplank": "77.60", "Graves": "33.35", "Gnar": "86.22", "Illaoi": "35.33", "Irelia": "84.55", "Janna": "69.89", "JarvanIV": "41.95", "Jayce": "80.31", "Jhin": "76.75", "Jinx": "88.17", "Karma": "61.95", "KogMaw": "51.37", "Leona": "65.19", "Lucian": "51.99", "Lulu": "74.32", "Malphite": "50.38", "MasterYi": "74.33", "Mordekaiser": "61.43", "Nautilus": "63.25", "Neeko": "51.33", "Nocturne": "37.47", "Poppy": "45.98", "Rakan": "48.92", "Rumble": "67.56", "Shaco": "57.67", "Shen": "55.70", "Syndra": "56.93", "Soraka": "65.41", "Riven": "83.81", "Teemo": "77.47", "Thresh": "81.80", "TwistedFate": "45.12", "Urgot": "74.25", "Vayne": "82.92", "Vi": "79.05", "Viktor": "78.63", "WuKong": "87.72", "Xayah": "49.43", "Xerath": "71.89", "XinZhao": "57.94", "Yasuo": "61.00", "Zed": "64.91", "Ziggs": "47.31", "Zoe": "44.17"}}